arcor2_yumi/VERSION
arcor2_yumi/__init__.py
arcor2_yumi/py.typed
arcor2_yumi-0.3.0.dist-info/METADATA
arcor2_yumi-0.3.0.dist-info/WHEEL
arcor2_yumi-0.3.0.dist-info/entry_points.txt
arcor2_yumi-0.3.0.dist-info/namespace_packages.txt
arcor2_yumi-0.3.0.dist-info/top_level.txt
arcor2_yumi-0.3.0.dist-info/RECORD
