Metadata-Version: 2.1
Name: arcor2-yumi
Version: 0.3.0
Summary: ARCOR2 Calibration
Author: Robo@FIT
Author-email: imaterna@fit.vut.cz
License: LGPL
Classifier: Development Status :: 3 - Alpha
Classifier: Intended Audience :: Developers
Classifier: Topic :: Software Development :: Build Tools
Classifier: License :: OSI Approved :: GNU Lesser General Public License v3 (LGPLv3)
Classifier: Programming Language :: Python :: 3.11
Classifier: Natural Language :: English
Classifier: Topic :: Scientific/Engineering
Requires-Python: ==3.11.*
Requires-Dist: arcor2-calibration-data (~=1.1.0)
Requires-Dist: arcor2-calibration (~=1.2.0)
Requires-Dist: arcor2 (~=1.3.0)
